[
    {
        "id": "meta_0",
        "platform": "meta",
        "title": "Log in to Meta for Business",
        "url": "",
        "date": "2026.04.16",
        "category": "notice",
        "productType": "all",
        "desc": "Meta 실제 공지사항입니다."
    },
    {
        "id": "meta_2",
        "platform": "meta",
        "title": "Removing Technical Barriers to Help Businesses of All Sizes Get More From Their Ads",
        "url": "",
        "date": "2026.04.16",
        "category": "notice",
        "productType": "all",
        "desc": "Meta 실제 공지사항입니다."
    },
    {
        "id": "meta_3",
        "platform": "meta",
        "title": "From Commerce to Culture: How AI is Powering Personalized Connection and Growth Across the Funnel",
        "url": "",
        "date": "2026.04.16",
        "category": "notice",
        "productType": "all",
        "desc": "Meta 실제 공지사항입니다."
    },
    {
        "id": "meta_4",
        "platform": "meta",
        "title": "Introducing a New Era of Product Discovery Powered by AI and Creators",
        "url": "",
        "date": "2026.04.16",
        "category": "notice",
        "productType": "all",
        "desc": "Meta 실제 공지사항입니다."
    }
]